pymnash/__init__.py
pymnash/game.py
pymnash/negadd.py
pymnash/sample_games.py
pymnash/stripped_poker.py
pymnash/util.py
pymnash-0.8.0.dist-info/METADATA
pymnash-0.8.0.dist-info/WHEEL
pymnash-0.8.0.dist-info/licenses/LICENSE
pymnash-0.8.0.dist-info/RECORD
