Metadata-Version: 2.1
Name: pymnash
Version: 0.8.0
Summary: Find Nash Equilibria of Multiplayer Games
Project-URL: Homepage, https://github.com/gmweinberg/pymnash
Project-URL: Issues, https://github.com/gmweinberg/pymnash/issues
Author-email: George Weinberg <gmweinberg@fastmail.fm>
License: BSD 3-Clause License
License-File: LICENSE
Keywords: game theory,nash,nash equilibria,nash equilibrium
Classifier: License :: OSI Approved :: BSD License
Classifier: Operating System :: OS Independent
Classifier: Programming Language :: Python :: 3
Requires-Python: >=3.8
Requires-Dist: numpy
Requires-Dist: sympy
